pykira/__init__.py
pykira/constants.py
pykira/module.py
pykira/receiver.py
pykira/utils.py
pykira-0.1.3.dist-info/LICENSE.md
pykira-0.1.3.dist-info/METADATA
pykira-0.1.3.dist-info/WHEEL
pykira-0.1.3.dist-info/top_level.txt
pykira-0.1.3.dist-info/RECORD
